sigauth/__init__.py
sigauth/helpers.py
sigauth/middleware.py
sigauth/permissions.py
sigauth-5.4.0.dist-info/licenses/LICENSE
sigauth-5.4.0.dist-info/METADATA
sigauth-5.4.0.dist-info/WHEEL
sigauth-5.4.0.dist-info/top_level.txt
sigauth-5.4.0.dist-info/RECORD
