Metadata-Version: 2.4
Name: sigauth
Version: 5.4.0
Summary: Signature authentication library for Export Directory.
Home-page: https://github.com/uktrade/directory-signature-auth
Author: Department for International Trade
License: MIT
Classifier: Development Status :: 5 - Production/Stable
Classifier: Environment :: Web Environment
Classifier: Framework :: Django
Classifier: Framework :: Django :: 1.11
Classifier: Framework :: Django :: 2.0
Classifier: Framework :: Django :: 2.1
Classifier: Framework :: Django :: 2.2
Classifier: Framework :: Django :: 3.1
Classifier: Framework :: Django :: 4.1
Classifier: Framework :: Django :: 4.2
Classifier: Intended Audience :: Developers
Classifier: License :: OSI Approved :: MIT License
Classifier: Natural Language :: English
Classifier: Operating System :: OS Independent
Classifier: Programming Language :: Python :: 3.5
Classifier: Programming Language :: Python :: 3.6
Classifier: Programming Language :: Python :: 3.9
Classifier: Programming Language :: Python :: 3.13
Classifier: Programming Language :: Python :: Implementation :: PyPy
Classifier: Topic :: Software Development :: Libraries :: Python Modules
License-File: LICENSE
Requires-Dist: django<5.0,>=4.2.10
Requires-Dist: djangorestframework<4.0.0,>=3.4.7
Requires-Dist: mohawk<2.0.0,>=0.3.4
Provides-Extra: test
Requires-Dist: pytest==7.*; extra == "test"
Requires-Dist: pytest-cov==4.*; extra == "test"
Requires-Dist: pytest-django==4.*; extra == "test"
Requires-Dist: flake8; extra == "test"
Requires-Dist: wheel<1.0.0,>=0.40.0; extra == "test"
Requires-Dist: setuptools; extra == "test"
Requires-Dist: codecov; extra == "test"
Requires-Dist: twine; extra == "test"
Dynamic: author
Dynamic: classifier
Dynamic: description
Dynamic: description-content-type
Dynamic: home-page
Dynamic: license
Dynamic: license-file
Dynamic: provides-extra
Dynamic: requires-dist
Dynamic: summary
